rickandmorty/__init__.py
rickandmorty/base.py
rickandmorty/character_client.py
rickandmorty/episode_client.py
rickandmorty/location_client.py
rickandmorty-0.1.0.dist-info/LICENSE
rickandmorty-0.1.0.dist-info/METADATA
rickandmorty-0.1.0.dist-info/WHEEL
rickandmorty-0.1.0.dist-info/top_level.txt
rickandmorty-0.1.0.dist-info/RECORD
