Metadata-Version: 2.1
Name: rickandmorty
Version: 0.1.0
Summary: Rick and Morty client for Rick and Morty API (https://rickandmortyapi.com/) 
Home-page: https://github.com/DogukanBaloglu/rickandmorty
Author: Dogukan Baloglu
Author-email: dogukanbaloglu99@gmail.com
License: MIT License
Keywords: rickandmorty
Platform: UNKNOWN
Classifier: Programming Language :: Python :: 3
Classifier: Programming Language :: Python :: 3.4
Classifier: Programming Language :: Python :: 3.5
Classifier: Programming Language :: Python :: 3.6
Classifier: Programming Language :: Python :: 3.7
Requires-Dist: requests
